<?xml version="1.0" encoding="ISO-8859-1"?>
<project
	xsi:schemaLocation="http://maven.apache.org/maven-navigation-1.0.xsd">
	<bannerLeft>
		<name>${project.name}</name>
	</bannerLeft>
	<version position="left" />
	<publishDate format="yyyy-MM-dd" position="left" />
	<skin>
		<groupId>org.apache.maven.skins</groupId>
		<artifactId>maven-stylus-skin</artifactId>
		<version>1.0.1</version>
	</skin>
	<body>
		<links>
			<item name="Xebia Home" href="http://www.xebia.fr/" />
			<item name="Xebia Blog" href="http://blog.xebia.fr" />
			<item name="Project Home" href="${project.scm.url}" />
			<item name="SVN" href="${project.scm.connection}" />
		</links>
		<menu name="Menu principal" collapse="false">
			<item name="Introduction" href="introduction.html" />
			<item name="FAQ" href="faq.html" />
			<item name="Releases" href="releases.html" />
		</menu>
		<menu ref="reports" collapse="false" />
		${reports}
		<menu name="Links" collapse="false">
			<item name="Xebia Home" href="http://www.xebia.fr/" />
			<item name="Xebia Blog" href="http://blog.xebia.fr" />
			<item name="Project Home" href="${project.scm.url}" />
			<item name="SVN" href="${project.scm.connection}" />
		</menu>
	</body>
</project>
